{"stats":{"minecraft:mined":{"minecraft:deepslate_redstone_ore":2,"minecraft:tuff":5,"minecraft:acacia_leaves":16,"minecraft:cherry_planks":2,"minecraft:deepslate_diamond_ore":5,"minecraft:cherry_log":23,"minecraft:cornflower":3,"minecraft:crafting_table":6,"minecraft:short_grass":306,"minecraft:acacia_log":46,"minecraft:grass_block":195,"minecraft:chest":1,"minecraft:copper_ore":1,"minecraft:tall_grass":27,"minecraft:cobblestone":2,"minecraft:lapis_ore":3,"minecraft:deepslate_gold_ore":5,"minecraft:diorite":4,"minecraft:amethyst_block":1,"minecraft:hay_block":39,"minecraft:smooth_stone":2,"minecraft:furnace":3,"minecraft:iron_ore":35,"minecraft:wheat":4,"minecraft:deepslate_lapis_ore":2,"minecraft:coal_ore":115,"minecraft:oak_log":26,"minecraft:water_cauldron":1,"minecraft:deepslate_iron_ore":52,"minecraft:cherry_leaves":36,"minecraft:dirt":23,"minecraft:stone":91,"minecraft:acacia_wall_sign":2,"minecraft:oak_leaves":13,"minecraft:deepslate":17,"minecraft:orange_bed":3},"minecraft:killed":{"minecraft:pig":1,"minecraft:spider":3,"minecraft:skeleton":5,"minecraft:zombie":12},"minecraft:picked_up":{"minecraft:pink_petals":2,"minecraft:crafting_table":7,"minecraft:wheat":3,"minecraft:cherry_planks":2,"minecraft:andesite":1,"minecraft:tuff":5,"minecraft:oak_log":26,"minecraft:gunpowder":2,"minecraft:golden_sword":1,"minecraft:cornflower":3,"minecraft:amethyst_block":1,"minecraft:lapis_lazuli":37,"minecraft:string":5,"minecraft:dirt":222,"minecraft:raw_copper":4,"minecraft:bone":7,"minecraft:apple":2,"minecraft:wheat_seeds":92,"minecraft:cobbled_deepslate":20,"minecraft:smooth_stone":2,"minecraft:raw_gold":5,"minecraft:bucket":1,"minecraft:acacia_sign":2,"minecraft:melon_slice":2,"minecraft:chest":1,"minecraft:acacia_sapling":6,"minecraft:egg":1,"minecraft:furnace":3,"minecraft:stick":14,"minecraft:raw_iron":85,"minecraft:torch":2,"minecraft:acacia_log":45,"minecraft:porkchop":3,"minecraft:cherry_log":29,"minecraft:diorite":3,"minecraft:carrot":1,"minecraft:redstone":8,"minecraft:cauldron":1,"minecraft:orange_bed":3,"minecraft:arrow":8,"minecraft:rotten_flesh":14,"minecraft:diamond":5,"minecraft:hay_block":38,"minecraft:shears":1,"minecraft:cherry_sapling":4,"minecraft:black_wool":3,"minecraft:bread":7,"minecraft:white_wool":4,"minecraft:oak_sapling":5,"minecraft:melon_seeds":5,"minecraft:coal":111,"minecraft:cobblestone":110},"minecraft:crafted":{"minecraft:cherry_planks":80,"minecraft:oak_planks":32,"minecraft:stone_shovel":2,"minecraft:crafting_table":4,"minecraft:iron_helmet":1,"minecraft:wooden_pickaxe":1,"minecraft:blue_bed":1,"minecraft:furnace":2,"minecraft:stone_axe":1,"minecraft:bread":30,"minecraft:air":0,"minecraft:blue_dye":3,"minecraft:iron_chestplate":1,"minecraft:diamond_pickaxe":1,"minecraft:acacia_sign":3,"minecraft:iron_hoe":1,"minecraft:stick":132,"minecraft:iron_ingot":81,"minecraft:iron_pickaxe":1,"minecraft:stone_pickaxe":2,"minecraft:blue_wool":3,"minecraft:stone_sword":2,"minecraft:chest":3,"minecraft:cherry_door":3,"minecraft:acacia_planks":68,"minecraft:torch":196,"minecraft:stone_hoe":1,"minecraft:wheat":90},"minecraft:dropped":{"minecraft:iron_ingot":1,"minecraft:tuff":5,"minecraft:amethyst_block":1,"minecraft:acacia_sign":1,"minecraft:torch":22},"minecraft:custom":{"minecraft:interact_with_furnace":12,"minecraft:mob_kills":22,"minecraft:interact_with_crafting_table":25,"minecraft:interact_with_grindstone":1,"minecraft:leave_game":5,"minecraft:time_since_death":133594,"minecraft:sleep_in_bed":6,"minecraft:time_since_rest":12204,"minecraft:sprint_one_cm":114702,"minecraft:damage_taken":1519,"minecraft:walk_one_cm":624963,"minecraft:drop":26,"minecraft:damage_dealt":4632,"minecraft:fly_one_cm":33403,"minecraft:open_chest":28,"minecraft:crouch_one_cm":1867,"minecraft:play_time":133594,"minecraft:sneak_time":669,"minecraft:walk_under_water_one_cm":5390,"minecraft:jump":1397,"minecraft:interact_with_brewingstand":1,"minecraft:interact_with_blast_furnace":1,"minecraft:walk_on_water_one_cm":25368,"minecraft:total_world_time":133594,"minecraft:fall_one_cm":15887},"minecraft:used":{"minecraft:wheat_seeds":58,"minecraft:water_bucket":3,"minecraft:diorite":3,"minecraft:stone_sword":147,"minecraft:stone_shovel":206,"minecraft:stone_pickaxe":227,"minecraft:oak_planks":12,"minecraft:chest":4,"minecraft:wooden_pickaxe":59,"minecraft:cauldron":1,"minecraft:cherry_planks":18,"minecraft:blue_bed":1,"minecraft:stone_hoe":65,"minecraft:orange_bed":3,"minecraft:torch":169,"minecraft:dirt":139,"minecraft:crafting_table":10,"minecraft:carrot":1,"minecraft:diamond_pickaxe":1,"minecraft:acacia_sign":3,"minecraft:cherry_door":3,"minecraft:bread":31,"minecraft:iron_pickaxe":72,"minecraft:melon_seeds":5,"minecraft:stone_axe":110,"minecraft:cobblestone":2,"minecraft:furnace":5,"minecraft:bucket":4,"minecraft:andesite":1,"minecraft:acacia_planks":1,"minecraft:cobbled_deepslate":1,"minecraft:smooth_stone":1},"minecraft:broken":{"minecraft:stone_pickaxe":1,"minecraft:stone_sword":1,"minecraft:stone_shovel":1,"minecraft:wooden_pickaxe":1}},"DataVersion":4189}